movemapp_client/__init__.py
movemapp_client/client.py
movemapp_client-0.1.1.dist-info/LICENSE
movemapp_client-0.1.1.dist-info/METADATA
movemapp_client-0.1.1.dist-info/WHEEL
movemapp_client-0.1.1.dist-info/top_level.txt
movemapp_client-0.1.1.dist-info/RECORD
