Metadata-Version: 2.1
Name: movemapp-client
Version: 0.1.1
Summary: A Python package for Movemapp client
Home-page: https://github.com/geografia-au/movemapp_client
Author: Shoaib Burq
Author-email: shoaib@geografia.com.au
Classifier: Development Status :: 3 - Alpha
Classifier: Intended Audience :: Developers
Classifier: Operating System :: OS Independent
Classifier: License :: OSI Approved :: MIT License
License-File: LICENSE
Requires-Dist: carto
Requires-Dist: python-dotenv
Provides-Extra: dev
Requires-Dist: pytest ; extra == 'dev'
Requires-Dist: python-dotenvautopep8 ; extra == 'dev'
